{
  "obsidian-hover-editor:bounce-popovers": [],
  "graph:open": [],
  "obsidian-excalidraw-plugin:Downloaded/Connect elements": [
    {
      "modifiers": [
        "Alt",
        "Ctrl"
      ],
      "key": "A"
    }
  ],
  "markdown-table-editor:markdown-table-editor-open-horizontal": [
    {
      "modifiers": [
        "Mod"
      ],
      "key": "T"
    }
  ],
  "obsidian-excalidraw-plugin:insert-link-to-element": [
    {
      "modifiers": [
        "Mod",
        "Shift"
      ],
      "key": "S"
    }
  ]
}